mypackage/__init__.py
mypackage/add.py
binarymans_mypackage-1.0.0.dist-info/METADATA
binarymans_mypackage-1.0.0.dist-info/WHEEL
binarymans_mypackage-1.0.0.dist-info/top_level.txt
binarymans_mypackage-1.0.0.dist-info/RECORD
