Metadata-Version: 2.4
Name: binarymans-mypackage
Version: 1.0.0
Summary: A simple package to add two numbers
Author-email: Rabbil <rabbil@jukti.io>
License: MIT
Project-URL: Homepage, https://github.com/rupomsoft/addtwo
Requires-Python: >=3.7
